punwrap-0.3.0.dist-info/METADATA
punwrap-0.3.0.dist-info/WHEEL
punwrap-0.3.0.dist-info/licenses/LICENSE
punwrap/__init__.py
punwrap/punwrap.cp310-win_amd64.pyd
punwrap-0.3.0.dist-info/RECORD
